mnara_test.py
mnara_test-0.0.2.dist-info/METADATA
mnara_test-0.0.2.dist-info/WHEEL
mnara_test-0.0.2.dist-info/entry_points.txt
mnara_test-0.0.2.dist-info/top_level.txt
mnara_test-0.0.2.dist-info/RECORD
