Metadata-Version: 2.1
Name: mnara-test
Version: 0.0.2
Summary: how to debut a PyPI for Chemistry
Home-page: https://github.com/mnara0613/mnara_test
Author: mnara0613
Author-email: mnara@sciencepark.co.jp
License: UNKNOWN
Project-URL: Bug Tracker, https://github.com/mnara0613/mnara_test
Platform: UNKNOWN
Classifier: Programming Language :: Python :: 3
Classifier: License :: OSI Approved :: MIT License
Requires-Python: >=3.8.10
